{
  "doc_type_name": "extra-gazettes",
  "id": "2110-27",
  "dir_data": "data/extra-gazettes/2019/2110-27",
  "doc_num": "2110/27",
  "date": "2019-02-13",
  "description": "Land Title Settlement Department - Hiripitiya, Attanagalla D/S Division, Gampaha District - Cad. Map No. 511609",
  "lang_to_source_url": {
    "en": "https://documents.gov.lk/view/extra-gazettes/2019/2/2110-27_E.pdf",
    "si": "https://documents.gov.lk/view/extra-gazettes/2019/2/2110-27_S.pdf",
    "ta": "https://documents.gov.lk/view/extra-gazettes/2019/2/2110-27_T.pdf"
  }
}