{
  "doc_type_name": "extra-gazettes",
  "id": "2407-34",
  "dir_data": "data/extra-gazettes/2024/2407-34",
  "doc_num": "2407/34",
  "date": "2024-10-24",
  "description": "Land Title Settlement Department - Wattarappala Village, Rathmalana D/S Division, Colombo District - Cad. Map No. 521006 (24/0865)",
  "lang_to_source_url": {
    "en": "https://documents.gov.lk/view/extra-gazettes/2024/10/2407-34_E.pdf",
    "si": "https://documents.gov.lk/view/extra-gazettes/2024/10/2407-34_S.pdf",
    "ta": "https://documents.gov.lk/view/extra-gazettes/2024/10/2407-34_T.pdf"
  }
}