{
  "doc_type_name": "extra-gazettes",
  "id": "2108-71",
  "dir_data": "data/extra-gazettes/2019/2108-71",
  "doc_num": "2108/71",
  "date": "2019-02-02",
  "description": "Presidential Secretariat - Mr. Sumith Abaysinghe appointed as Secretary to the President (Temporary) With effcet  from 30.01.2019 until Mr. Udaya R. Seneviratne returns to the Island",
  "lang_to_source_url": {
    "en": "https://documents.gov.lk/view/extra-gazettes/2019/2/2108-71_E.pdf",
    "si": "https://documents.gov.lk/view/extra-gazettes/2019/2/2108-71_S.pdf",
    "ta": "https://documents.gov.lk/view/extra-gazettes/2019/2/2108-71_T.pdf"
  }
}