{
  "doc_type_name": "extra-gazettes",
  "id": "1983-05",
  "dir_data": "data/extra-gazettes/2016/1983-05",
  "doc_num": "1983/05",
  "date": "2016-09-05",
  "description": "Land Acquisition - P. P. No. Ma/1613 of Matale Town, Matale D/S Division, Matale District",
  "lang_to_source_url": {
    "en": "https://documents.gov.lk/view/extra-gazettes/2016/9/1983-05_E.pdf",
    "si": "https://documents.gov.lk/view/extra-gazettes/2016/9/1983-05_S.pdf",
    "ta": "https://documents.gov.lk/view/extra-gazettes/2016/9/1983-05_T.pdf"
  }
}