{
  "doc_type_name": "extra-gazettes",
  "id": "1772-31",
  "dir_data": "data/extra-gazettes/2012/1772-31",
  "doc_num": "1772/31",
  "date": "2012-08-22",
  "description": "Land Acquisition - Medapihilla, Nawanaliya (Ma/Nu/2008/242, Ma/Nu1/2008/295, Galporugolla,Medapihilla D/S Division Naula, Matale District",
  "lang_to_source_url": {
    "en": "https://documents.gov.lk/view/extra-gazettes/2012/8/1772-31_E.pdf",
    "si": "https://documents.gov.lk/view/extra-gazettes/2012/8/1772-31_S.pdf",
    "ta": "https://documents.gov.lk/view/extra-gazettes/2012/8/1772-31_T.pdf"
  }
}