{
  "doc_type_name": "extra-gazettes",
  "id": "2003-42",
  "dir_data": "data/extra-gazettes/2017/2003-42",
  "doc_num": "2003/42",
  "date": "2017-01-27",
  "description": "Land Acquisition - Block No. 2 & 4, Sooripaluwa & Ihalakaragahamuna, Mahara D/S Division, Gampaha District and Amendment to the Ex. Ord. Gaz. No. 2001/9 of 11.01.2017, Kobeigane D/S Division.",
  "lang_to_source_url": {
    "en": "https://documents.gov.lk/view/extra-gazettes/2017/1/2003-42_E.pdf",
    "si": "https://documents.gov.lk/view/extra-gazettes/2017/1/2003-42_S.pdf",
    "ta": "https://documents.gov.lk/view/extra-gazettes/2017/1/2003-42_T.pdf"
  }
}