{
  "doc_type_name": "extra-gazettes",
  "id": "1934-34",
  "dir_data": "data/extra-gazettes/2015/1934-34",
  "doc_num": "1934/34",
  "date": "2015-10-02",
  "description": "Department of Fiscal Policy - Notifying that the Mid Year Fiscal Position Report 2015 is available for inspection at the Office of Superintendent, Government Publication Bureau",
  "lang_to_source_url": {
    "en": "https://documents.gov.lk/view/extra-gazettes/2015/10/1934-34_E.pdf",
    "si": "https://documents.gov.lk/view/extra-gazettes/2015/10/1934-34_S.pdf",
    "ta": "https://documents.gov.lk/view/extra-gazettes/2015/10/1934-34_T.pdf"
  }
}