{
  "doc_type_name": "extra-gazettes",
  "id": "2283-31",
  "dir_data": "data/extra-gazettes/2022/2283-31",
  "doc_num": "2283/31",
  "date": "2022-06-08",
  "description": "Land Acquisition - Kumbutukuliya, Arachchikattuwa D/S Division, Puttalam District",
  "lang_to_source_url": {
    "en": "https://documents.gov.lk/view/extra-gazettes/2022/6/2283-31_E.pdf",
    "si": "https://documents.gov.lk/view/extra-gazettes/2022/6/2283-31_S.pdf",
    "ta": "https://documents.gov.lk/view/extra-gazettes/2022/6/2283-31_T.pdf"
  }
}