{
  "doc_type_name": "extra-gazettes",
  "id": "1802-11",
  "dir_data": "data/extra-gazettes/2013/1802-11",
  "doc_num": "1802/11",
  "date": "2013-03-20",
  "description": "Land Acquisition - Elagamuwa, Naula D/S Division, Matale District (Sheet No. 34) - Elagamuwa, Naula D/S Division, (Sheet No. 35) - Tholambagolla, Galewela D/S Division, Matale District - Uswetakeiyawa, Wattala D/S Division, Gampaha District",
  "lang_to_source_url": {
    "en": "https://documents.gov.lk/view/extra-gazettes/2013/3/1802-11_E.pdf",
    "si": "https://documents.gov.lk/view/extra-gazettes/2013/3/1802-11_S.pdf",
    "ta": "https://documents.gov.lk/view/extra-gazettes/2013/3/1802-11_T.pdf"
  }
}