{
  "doc_type_name": "extra-gazettes",
  "id": "2396-04",
  "dir_data": "data/extra-gazettes/2024/2396-04",
  "doc_num": "2396/04",
  "date": "2024-08-05",
  "description": "Presidential Secretartiate - An Essential Public Service to the life of Community - 1. All Services Connected to the Supply of Electricity. 2. The Supply or Distribution of Petroleum Products and Fuel.",
  "lang_to_source_url": {
    "en": "https://documents.gov.lk/view/extra-gazettes/2024/8/2396-04_E.pdf",
    "si": "https://documents.gov.lk/view/extra-gazettes/2024/8/2396-04_S.pdf",
    "ta": "https://documents.gov.lk/view/extra-gazettes/2024/8/2396-04_T.pdf"
  }
}