{
  "doc_type_name": "extra-gazettes",
  "id": "1849-31",
  "dir_data": "data/extra-gazettes/2014/1849-31",
  "doc_num": "1849/31",
  "date": "2014-02-13",
  "description": "Ministry of Defence and Urban Development - Subsequent Amendments to the Consolidated List under Regulation 4(2)(b) of the United nations Regulations No. 2 of 2012",
  "lang_to_source_url": {
    "en": "https://documents.gov.lk/view/extra-gazettes/2014/2/1849-31_E.pdf",
    "si": "https://documents.gov.lk/view/extra-gazettes/2014/2/1849-31_S.pdf",
    "ta": "https://documents.gov.lk/view/extra-gazettes/2014/2/1849-31_T.pdf"
  }
}