{
  "doc_type_name": "extra-gazettes",
  "id": "2421-36",
  "dir_data": "data/extra-gazettes/2025/2421-36",
  "doc_num": "2421/36",
  "date": "2025-01-31",
  "description": "Land Title Settlement Dept. -Gampaha Aluthgama, Gampaha  D/S Division, Gampaha District - Cad. Map No.511827 (7772)",
  "lang_to_source_url": {
    "en": "https://documents.gov.lk/view/extra-gazettes/2025/1/2421-36_E.pdf",
    "si": "https://documents.gov.lk/view/extra-gazettes/2025/1/2421-36_S.pdf",
    "ta": "https://documents.gov.lk/view/extra-gazettes/2025/1/2421-36_T.pdf"
  }
}