{
  "doc_type_name": "extra-gazettes",
  "id": "1713-05",
  "dir_data": "data/extra-gazettes/2011/1713-05",
  "doc_num": "1713/05",
  "date": "2011-07-05",
  "description": "Land Acquisition - Ihalagoda (supplement 56, 57), Akmeemana D/S Division, Galle District - Pahala Keembiya, Baddegama D/S Division, Galle District - Kurundugahahathakma, Karandeniya D/S Division, Galle District - Godigamuwa, Horana  D/S Division, Kalutara District",
  "lang_to_source_url": {
    "en": "https://documents.gov.lk/view/extra-gazettes/2011/7/1713-05_E.pdf",
    "si": "https://documents.gov.lk/view/extra-gazettes/2011/7/1713-05_S.pdf",
    "ta": "https://documents.gov.lk/view/extra-gazettes/2011/7/1713-05_T.pdf"
  }
}