{
  "doc_type_name": "extra-gazettes",
  "id": "2255-33",
  "dir_data": "data/extra-gazettes/2021/2255-33",
  "doc_num": "2255/33",
  "date": "2021-11-25",
  "description": "Land Title Settlement Department - Walpita, Divulapitiya D/S Division, Gampaha District - Cad. Map No. 510004",
  "lang_to_source_url": {
    "en": "https://documents.gov.lk/view/extra-gazettes/2021/11/2255-33_E.pdf",
    "si": "https://documents.gov.lk/view/extra-gazettes/2021/11/2255-33_S.pdf",
    "ta": "https://documents.gov.lk/view/extra-gazettes/2021/11/2255-33_T.pdf"
  }
}