{
  "doc_type_name": "extra-gazettes",
  "id": "1837-27",
  "dir_data": "data/extra-gazettes/2013/1837-27",
  "doc_num": "1837/27",
  "date": "2013-11-21",
  "description": "Dept. of Trade & Investment Policy - Order to inform the public of the Depreciation Table for the valuation of used Motor Vehicles with effect from 22.11.2013",
  "lang_to_source_url": {
    "en": "https://documents.gov.lk/view/extra-gazettes/2013/11/1837-27_E.pdf",
    "si": "https://documents.gov.lk/view/extra-gazettes/2013/11/1837-27_S.pdf",
    "ta": "https://documents.gov.lk/view/extra-gazettes/2013/11/1837-27_T.pdf"
  }
}