{
  "doc_type_name": "extra-gazettes",
  "id": "2342-29",
  "dir_data": "data/extra-gazettes/2023/2342-29",
  "doc_num": "2342/29",
  "date": "2023-07-27",
  "description": "Central Bank of Sri Lanka - Advertisement of Petition - Winding up of ETI Finance Limited",
  "lang_to_source_url": {
    "en": "https://documents.gov.lk/view/extra-gazettes/2023/7/2342-29_E.pdf",
    "si": "https://documents.gov.lk/view/extra-gazettes/2023/7/2342-29_S.pdf",
    "ta": "https://documents.gov.lk/view/extra-gazettes/2023/7/2342-29_T.pdf"
  }
}