{
  "doc_type_name": "extra-gazettes",
  "id": "1886-22",
  "dir_data": "data/extra-gazettes/2014/1886-22",
  "doc_num": "1886/22",
  "date": "2014-10-28",
  "description": "Land Title Settlement Department - Siddhamulla, Homagama D/S Division, Colombo District - Cad. Map No. 520020",
  "lang_to_source_url": {
    "en": "https://documents.gov.lk/view/extra-gazettes/2014/10/1886-22_E.pdf",
    "si": "https://documents.gov.lk/view/extra-gazettes/2014/10/1886-22_S.pdf",
    "ta": "https://documents.gov.lk/view/extra-gazettes/2014/10/1886-22_T.pdf"
  }
}