{
  "doc_type_name": "extra-gazettes",
  "id": "2105-61",
  "dir_data": "data/extra-gazettes/2019/2105-61",
  "doc_num": "2105/61",
  "date": "2019-01-11",
  "description": "Land Title Settlement Department - Hanchapola, Meerigama D/S Division, Gampaha District - Cad. Map No. 510202",
  "lang_to_source_url": {
    "en": "https://documents.gov.lk/view/extra-gazettes/2019/1/2105-61_E.pdf",
    "si": "https://documents.gov.lk/view/extra-gazettes/2019/1/2105-61_S.pdf",
    "ta": "https://documents.gov.lk/view/extra-gazettes/2019/1/2105-61_T.pdf"
  }
}