{
  "doc_type_name": "extra-gazettes",
  "id": "2378-11",
  "dir_data": "data/extra-gazettes/2024/2378-11",
  "doc_num": "2378/11",
  "date": "2024-04-01",
  "description": "Land Title Settlement Department - Kirindigala, Balangoda D/S Division, Rathnapura District - Cad. Map No. 620074 (24/0213)",
  "lang_to_source_url": {
    "en": "https://documents.gov.lk/view/extra-gazettes/2024/4/2378-11_E.pdf",
    "si": "https://documents.gov.lk/view/extra-gazettes/2024/4/2378-11_S.pdf",
    "ta": "https://documents.gov.lk/view/extra-gazettes/2024/4/2378-11_T.pdf"
  }
}