{
  "doc_type_name": "extra-gazettes",
  "id": "2317-48",
  "dir_data": "data/extra-gazettes/2023/2317-48",
  "doc_num": "2317/48",
  "date": "2023-01-30",
  "description": "Land Title Settlement Department - Horagasmulla, Divulapitiya D/S Division, Gampaha District - Cad. Map No. 510015 (22/0744)",
  "lang_to_source_url": {
    "en": "https://documents.gov.lk/view/extra-gazettes/2023/1/2317-48_E.pdf",
    "si": "https://documents.gov.lk/view/extra-gazettes/2023/1/2317-48_S.pdf",
    "ta": "https://documents.gov.lk/view/extra-gazettes/2023/1/2317-48_T.pdf"
  }
}