{
  "doc_type_name": "extra-gazettes",
  "id": "2403-28",
  "dir_data": "data/extra-gazettes/2024/2403-28",
  "doc_num": "2403/28",
  "date": "2024-09-28",
  "description": "Minister of Water Supply and Estate Intrastate Development - The Upcountry Charter - 2024.",
  "lang_to_source_url": {
    "en": "https://documents.gov.lk/view/extra-gazettes/2024/9/2403-28_E.pdf",
    "si": "https://documents.gov.lk/view/extra-gazettes/2024/9/2403-28_S.pdf",
    "ta": "https://documents.gov.lk/view/extra-gazettes/2024/9/2403-28_T.pdf"
  }
}