{
  "doc_type_name": "extra-gazettes",
  "id": "2065-19",
  "dir_data": "data/extra-gazettes/2018/2065-19",
  "doc_num": "2065/19",
  "date": "2018-04-03",
  "description": "Uva Provincial Council - Notify the appointment of the Authorized Officer for Badulla & Monaragala Districts under the Rent Act",
  "lang_to_source_url": {
    "en": "https://documents.gov.lk/view/extra-gazettes/2018/4/2065-19_E.pdf",
    "si": "https://documents.gov.lk/view/extra-gazettes/2018/4/2065-19_S.pdf",
    "ta": "https://documents.gov.lk/view/extra-gazettes/2018/4/2065-19_T.pdf"
  }
}