{
  "doc_type_name": "extra-gazettes",
  "id": "2068-45",
  "dir_data": "data/extra-gazettes/2018/2068-45",
  "doc_num": "2068/45",
  "date": "2018-04-27",
  "description": "Ministry of Provincial  Council and Local Government -  Amendment to the Ex. Gaz. No. 2043/56 of 02.11.2017 Elpitiya P/S",
  "lang_to_source_url": {
    "en": "https://documents.gov.lk/view/extra-gazettes/2018/4/2068-45_E.pdf",
    "si": "https://documents.gov.lk/view/extra-gazettes/2018/4/2068-45_S.pdf",
    "ta": "https://documents.gov.lk/view/extra-gazettes/2018/4/2068-45_T.pdf"
  }
}