{
  "doc_type_name": "extra-gazettes",
  "id": "2209-61",
  "dir_data": "data/extra-gazettes/2021/2209-61",
  "doc_num": "2209/61",
  "date": "2021-01-07",
  "description": "Land Title Settlement Department - Wegiriya, Udunuwara D/S Division, Kandy District - Cad. Map No. 320243",
  "lang_to_source_url": {
    "en": "https://documents.gov.lk/view/extra-gazettes/2021/1/2209-61_E.pdf",
    "si": "https://documents.gov.lk/view/extra-gazettes/2021/1/2209-61_S.pdf",
    "ta": "https://documents.gov.lk/view/extra-gazettes/2021/1/2209-61_T.pdf"
  }
}