{
  "doc_type_name": "extra-gazettes",
  "id": "1766-32",
  "dir_data": "data/extra-gazettes/2012/1766-32",
  "doc_num": "1766/32",
  "date": "2012-07-13",
  "description": "Central Bank of Sri Lanka - Finance Companies (Interest Rates) Direction No. 3 of 2012",
  "lang_to_source_url": {
    "en": "https://documents.gov.lk/view/extra-gazettes/2012/7/1766-32_E.pdf",
    "si": "https://documents.gov.lk/view/extra-gazettes/2012/7/1766-32_S.pdf",
    "ta": "https://documents.gov.lk/view/extra-gazettes/2012/7/1766-32_T.pdf"
  }
}