{
  "doc_type_name": "extra-gazettes",
  "id": "2166-51",
  "dir_data": "data/extra-gazettes/2020/2166-51",
  "doc_num": "2166/51",
  "date": "2020-03-15",
  "description": "Ministry of Public Administration, Home Affairs - Order to declare Monday 16th of March, 2020 a Public and Bank Special Holiday to Support Quarantine Process on Corona Virus, This Holiday will be extending if necessary",
  "lang_to_source_url": {
    "en": "https://documents.gov.lk/view/extra-gazettes/2020/3/2166-51_E.pdf",
    "si": "https://documents.gov.lk/view/extra-gazettes/2020/3/2166-51_S.pdf",
    "ta": "https://documents.gov.lk/view/extra-gazettes/2020/3/2166-51_T.pdf"
  }
}