{
  "doc_type_name": "extra-gazettes",
  "id": "2348-23",
  "dir_data": "data/extra-gazettes/2023/2348-23",
  "doc_num": "2348/23",
  "date": "2023-09-05",
  "description": "Mediation Boards Commission - Notice of Calling for Nominations to appoint persons to be Mediators",
  "lang_to_source_url": {
    "en": "https://documents.gov.lk/view/extra-gazettes/2023/9/2348-23_E.pdf",
    "si": "https://documents.gov.lk/view/extra-gazettes/2023/9/2348-23_S.pdf",
    "ta": "https://documents.gov.lk/view/extra-gazettes/2023/9/2348-23_T.pdf"
  }
}