{
  "doc_type_name": "extra-gazettes",
  "id": "2377-40",
  "dir_data": "data/extra-gazettes/2024/2377-40",
  "doc_num": "2377/40",
  "date": "2024-03-28",
  "description": "Department of Archaeology - The Antiquities Ordinance (Chapter 188) The order made under Section 18 (The Monuments to be declared as protected Monuments - Antiquities Ordinance (Chapter 188) Order made under Section 16 (The list of Monuments which shall be declared as Ancient Monuments)",
  "lang_to_source_url": {
    "en": "https://documents.gov.lk/view/extra-gazettes/2024/3/2377-40_E.pdf",
    "si": "https://documents.gov.lk/view/extra-gazettes/2024/3/2377-40_S.pdf",
    "ta": "https://documents.gov.lk/view/extra-gazettes/2024/3/2377-40_T.pdf"
  }
}