{
  "doc_type_name": "extra-gazettes",
  "id": "2017-42",
  "dir_data": "data/extra-gazettes/2017/2017-42",
  "doc_num": "2017/42",
  "date": "2017-05-05",
  "description": "Chief Secretariate's Office - Central Province - Central Province Provincial Council on 21.02.2017 under section 125 of the said Act, read together with section (3) of section z of the Provincial Coucils (Consequential Provisions) Act, No. 12 of 1989",
  "lang_to_source_url": {
    "en": "https://documents.gov.lk/view/extra-gazettes/2017/5/2017-42_E.pdf",
    "si": "https://documents.gov.lk/view/extra-gazettes/2017/5/2017-42_S.pdf",
    "ta": "https://documents.gov.lk/view/extra-gazettes/2017/5/2017-42_T.pdf"
  }
}