{
  "doc_type_name": "extra-gazettes",
  "id": "1842-06",
  "dir_data": "data/extra-gazettes/2013/1842-06",
  "doc_num": "1842/06",
  "date": "2013-12-24",
  "description": "Land Acquisition - Ihala Thalawa/Moragoda, Thalawa D/S Division, Anuradhapura District",
  "lang_to_source_url": {
    "en": "https://documents.gov.lk/view/extra-gazettes/2013/12/1842-06_E.pdf",
    "si": "https://documents.gov.lk/view/extra-gazettes/2013/12/1842-06_S.pdf",
    "ta": "https://documents.gov.lk/view/extra-gazettes/2013/12/1842-06_T.pdf"
  }
}