{
  "doc_type_name": "extra-gazettes",
  "id": "2143-22",
  "dir_data": "data/extra-gazettes/2019/2143-22",
  "doc_num": "2143/22",
  "date": "2019-10-02",
  "description": "Land Acquisition - Thennekumbura, Kandy Four Gravets D/S Division, Kandy District and Batugammana, Monaragala D/S Division, Monaragala District",
  "lang_to_source_url": {
    "en": "https://documents.gov.lk/view/extra-gazettes/2019/10/2143-22_E.pdf",
    "si": "https://documents.gov.lk/view/extra-gazettes/2019/10/2143-22_S.pdf",
    "ta": "https://documents.gov.lk/view/extra-gazettes/2019/10/2143-22_T.pdf"
  }
}