{
  "doc_type_name": "extra-gazettes",
  "id": "2087-11",
  "dir_data": "data/extra-gazettes/2018/2087-11",
  "doc_num": "2087/11",
  "date": "2018-09-03",
  "description": "Land Acquisition - Notify the compensation for the acquisitions of land in Karadagahamula Wattha, Kundasale D/S Division",
  "lang_to_source_url": {
    "en": "https://documents.gov.lk/view/extra-gazettes/2018/9/2087-11_E.pdf",
    "si": "https://documents.gov.lk/view/extra-gazettes/2018/9/2087-11_S.pdf",
    "ta": "https://documents.gov.lk/view/extra-gazettes/2018/9/2087-11_T.pdf"
  }
}