{
  "doc_type_name": "extra-gazettes",
  "id": "2430-35",
  "dir_data": "data/extra-gazettes/2025/2430-35",
  "doc_num": "2430/35",
  "date": "2025-04-04",
  "description": "Ministry of Labour - Industrial Disputer Between K.M.G. Upali Jayathilaka and National Housing Development Authority. Industrial Disputer Between Suadeena Moter Ratha Sewaka Samithiya and Sri Lanka Transport Board.",
  "lang_to_source_url": {
    "en": "https://documents.gov.lk/view/extra-gazettes/2025/4/2430-35_E.pdf",
    "si": "https://documents.gov.lk/view/extra-gazettes/2025/4/2430-35_S.pdf"
  }
}