{
  "doc_type_name": "extra-gazettes",
  "id": "2383-05",
  "dir_data": "data/extra-gazettes/2024/2383-05",
  "doc_num": "2383/05",
  "date": "2024-05-06",
  "description": "Ministry of Wild Life and Forest Resources Conservation - Order to declare that the Area of State Land In Mannar District as the Wedithalathie Nature Reserve",
  "lang_to_source_url": {
    "en": "https://documents.gov.lk/view/extra-gazettes/2024/5/2383-05_E.pdf",
    "si": "https://documents.gov.lk/view/extra-gazettes/2024/5/2383-05_S.pdf",
    "ta": "https://documents.gov.lk/view/extra-gazettes/2024/5/2383-05_T.pdf"
  }
}