{
  "doc_type_name": "extra-gazettes",
  "id": "1841-33",
  "dir_data": "data/extra-gazettes/2013/1841-33",
  "doc_num": "1841/33",
  "date": "2013-12-20",
  "description": "Land Title Settlement Dept. - Suwarapola, Kesbewa D/S Division, Colombo District - Cad. Map No. 521201",
  "lang_to_source_url": {
    "en": "https://documents.gov.lk/view/extra-gazettes/2013/12/1841-33_E.pdf",
    "si": "https://documents.gov.lk/view/extra-gazettes/2013/12/1841-33_S.pdf",
    "ta": "https://documents.gov.lk/view/extra-gazettes/2013/12/1841-33_T.pdf"
  }
}