{
  "doc_type_name": "extra-gazettes",
  "id": "2054-50",
  "dir_data": "data/extra-gazettes/2018/2054-50",
  "doc_num": "2054/50",
  "date": "2018-01-18",
  "description": "Land Acquisition - Varani, Thenmarachchi D/S Division, Jaffna District",
  "lang_to_source_url": {
    "en": "https://documents.gov.lk/view/extra-gazettes/2018/1/2054-50_E.pdf",
    "si": "https://documents.gov.lk/view/extra-gazettes/2018/1/2054-50_S.pdf",
    "ta": "https://documents.gov.lk/view/extra-gazettes/2018/1/2054-50_T.pdf"
  }
}