{
  "doc_type_name": "extra-gazettes",
  "id": "2151-43",
  "dir_data": "data/extra-gazettes/2019/2151-43",
  "doc_num": "2151/43",
  "date": "2019-11-28",
  "description": "Land Title Settlement Department - Mailawalana, Dompe D/S Division, Gampaha District - Cad. Map No. 511000 and others",
  "lang_to_source_url": {
    "en": "https://documents.gov.lk/view/extra-gazettes/2019/11/2151-43_E.pdf",
    "si": "https://documents.gov.lk/view/extra-gazettes/2019/11/2151-43_S.pdf",
    "ta": "https://documents.gov.lk/view/extra-gazettes/2019/11/2151-43_T.pdf"
  }
}