{
  "doc_type_name": "extra-gazettes",
  "id": "2307-72",
  "dir_data": "data/extra-gazettes/2022/2307-72",
  "doc_num": "2307/72",
  "date": "2022-11-26",
  "description": "Land Title Settlement Department - Attidiya South, Rathmalana D/S Division, Colombo District - Cad. Map No. 521002",
  "lang_to_source_url": {
    "en": "https://documents.gov.lk/view/extra-gazettes/2022/11/2307-72_E.pdf",
    "si": "https://documents.gov.lk/view/extra-gazettes/2022/11/2307-72_S.pdf",
    "ta": "https://documents.gov.lk/view/extra-gazettes/2022/11/2307-72_T.pdf"
  }
}