{
  "doc_type_name": "extra-gazettes",
  "id": "1725-23",
  "dir_data": "data/extra-gazettes/2011/1725-23",
  "doc_num": "1725/23",
  "date": "2011-09-30",
  "description": "Ministry of Defence - Places of detection for the purposes of sec 9 of the Prevention of Terroism (Temporory Provisions) Act.No. 48 of 1979. Boossa detention place, Boossa Vavuniya District criminal Investigation Division",
  "lang_to_source_url": {
    "en": "https://documents.gov.lk/view/extra-gazettes/2011/9/1725-23_E.pdf",
    "si": "https://documents.gov.lk/view/extra-gazettes/2011/9/1725-23_S.pdf",
    "ta": "https://documents.gov.lk/view/extra-gazettes/2011/9/1725-23_T.pdf"
  }
}