{
  "doc_type_name": "extra-gazettes",
  "id": "2302-11",
  "dir_data": "data/extra-gazettes/2022/2302-11",
  "doc_num": "2302/11",
  "date": "2022-10-18",
  "description": "Land Acquisition - Galaha, Delthota D/S Division, Kandy District",
  "lang_to_source_url": {
    "en": "https://documents.gov.lk/view/extra-gazettes/2022/10/2302-11_E.pdf",
    "si": "https://documents.gov.lk/view/extra-gazettes/2022/10/2302-11_S.pdf",
    "ta": "https://documents.gov.lk/view/extra-gazettes/2022/10/2302-11_T.pdf"
  }
}