{
  "doc_type_name": "extra-gazettes",
  "id": "2121-47",
  "dir_data": "data/extra-gazettes/2019/2121-47",
  "doc_num": "2121/47",
  "date": "2019-05-02",
  "description": "Elections Commission - Declare that T. L. T. Jawfer as a Member of the Kattankudy Urban Council",
  "lang_to_source_url": {
    "en": "https://documents.gov.lk/view/extra-gazettes/2019/5/2121-47_E.pdf",
    "si": "https://documents.gov.lk/view/extra-gazettes/2019/5/2121-47_S.pdf",
    "ta": "https://documents.gov.lk/view/extra-gazettes/2019/5/2121-47_T.pdf"
  }
}