{
  "doc_type_name": "extra-gazettes",
  "id": "1993-23",
  "dir_data": "data/extra-gazettes/2016/1993-23",
  "doc_num": "1993/23",
  "date": "2016-11-17",
  "description": "Ministry of Home Affairs - Regulations of Suwa Sahanaya Catholic Church in Weligama D/S Division, Matara District",
  "lang_to_source_url": {
    "en": "https://documents.gov.lk/view/extra-gazettes/2016/11/1993-23_E.pdf",
    "si": "https://documents.gov.lk/view/extra-gazettes/2016/11/1993-23_S.pdf",
    "ta": "https://documents.gov.lk/view/extra-gazettes/2016/11/1993-23_T.pdf"
  }
}