{
  "doc_type_name": "extra-gazettes",
  "id": "2348-29",
  "dir_data": "data/extra-gazettes/2023/2348-29",
  "doc_num": "2348/29",
  "date": "2023-09-06",
  "description": "Land Title Settlement Department - Maligathenna, Kandy Four and Gravest, Gangawatakorale D/S Division, Kandy District - Cad. Map No. 320290 (23/632)",
  "lang_to_source_url": {
    "en": "https://documents.gov.lk/view/extra-gazettes/2023/9/2348-29_E.pdf",
    "si": "https://documents.gov.lk/view/extra-gazettes/2023/9/2348-29_S.pdf",
    "ta": "https://documents.gov.lk/view/extra-gazettes/2023/9/2348-29_T.pdf"
  }
}