{
  "doc_type_name": "extra-gazettes",
  "id": "1871-46",
  "dir_data": "data/extra-gazettes/2014/1871-46",
  "doc_num": "1871/46",
  "date": "2014-07-19",
  "description": "Ministry of Elections - Elected Mr. Arulanantham Rajeevan as a member of the Valikamam East P/S",
  "lang_to_source_url": {
    "en": "https://documents.gov.lk/view/extra-gazettes/2014/7/1871-46_E.pdf",
    "si": "https://documents.gov.lk/view/extra-gazettes/2014/7/1871-46_S.pdf",
    "ta": "https://documents.gov.lk/view/extra-gazettes/2014/7/1871-46_T.pdf"
  }
}