{
  "doc_type_name": "extra-gazettes",
  "id": "1818-20",
  "dir_data": "data/extra-gazettes/2013/1818-20",
  "doc_num": "1818/20",
  "date": "2013-07-11",
  "description": "Department of Labour - Summon the objections for the proposed Wages Board for the Paddy Hulling Trade",
  "lang_to_source_url": {
    "en": "https://documents.gov.lk/view/extra-gazettes/2013/7/1818-20_E.pdf",
    "si": "https://documents.gov.lk/view/extra-gazettes/2013/7/1818-20_S.pdf",
    "ta": "https://documents.gov.lk/view/extra-gazettes/2013/7/1818-20_T.pdf"
  }
}