{
  "doc_type_name": "extra-gazettes",
  "id": "1739-34",
  "dir_data": "data/extra-gazettes/2012/1739-34",
  "doc_num": "1739/34",
  "date": "2012-01-06",
  "description": "Land Acquisition - Karandamulla (Lot 28, Lot 50) Laggala-Pallegama D/S Division, Matale District",
  "lang_to_source_url": {
    "en": "https://documents.gov.lk/view/extra-gazettes/2012/1/1739-34_E.pdf",
    "si": "https://documents.gov.lk/view/extra-gazettes/2012/1/1739-34_S.pdf",
    "ta": "https://documents.gov.lk/view/extra-gazettes/2012/1/1739-34_T.pdf"
  }
}