{
  "doc_type_name": "extra-gazettes",
  "id": "1958-39",
  "dir_data": "data/extra-gazettes/2016/1958-39",
  "doc_num": "1958/39",
  "date": "2016-03-18",
  "description": "Land Title Settlement Department - Henegama, Horana D/S Division, Kalutara District - Cad. Map No. 530178",
  "lang_to_source_url": {
    "en": "https://documents.gov.lk/view/extra-gazettes/2016/3/1958-39_E.pdf",
    "si": "https://documents.gov.lk/view/extra-gazettes/2016/3/1958-39_S.pdf",
    "ta": "https://documents.gov.lk/view/extra-gazettes/2016/3/1958-39_T.pdf"
  }
}