{
  "doc_type_name": "extra-gazettes",
  "id": "2004-11",
  "dir_data": "data/extra-gazettes/2017/2004-11",
  "doc_num": "2004/11",
  "date": "2017-01-30",
  "description": "Land Title Settlement Dept. - Homagama, Homagama D/S Division, Colombo District - Cad. Map No. 520001",
  "lang_to_source_url": {
    "en": "https://documents.gov.lk/view/extra-gazettes/2017/1/2004-11_E.pdf",
    "si": "https://documents.gov.lk/view/extra-gazettes/2017/1/2004-11_S.pdf",
    "ta": "https://documents.gov.lk/view/extra-gazettes/2017/1/2004-11_T.pdf"
  }
}