{
  "doc_type_name": "extra-gazettes",
  "id": "1700-02",
  "dir_data": "data/extra-gazettes/2011/1700-02",
  "doc_num": "1700/02",
  "date": "2011-04-04",
  "description": "Presidential Secretariat - Appointment of Mr. Warunasiri Mahinda Deshapriya as Commissioner of Elections w.e.f. 25.03.2011",
  "lang_to_source_url": {
    "en": "https://documents.gov.lk/view/extra-gazettes/2011/4/1700-02_E.pdf",
    "si": "https://documents.gov.lk/view/extra-gazettes/2011/4/1700-02_S.pdf",
    "ta": "https://documents.gov.lk/view/extra-gazettes/2011/4/1700-02_T.pdf"
  }
}