{
  "doc_type_name": "extra-gazettes",
  "id": "2268-37",
  "dir_data": "data/extra-gazettes/2022/2268-37",
  "doc_num": "2268/37",
  "date": "2022-02-22",
  "description": "Land Title Settlement Department - Medawala, Harispaththuwa D/S Division, Kandy District - Cad. Map No. 320465",
  "lang_to_source_url": {
    "en": "https://documents.gov.lk/view/extra-gazettes/2022/2/2268-37_E.pdf",
    "si": "https://documents.gov.lk/view/extra-gazettes/2022/2/2268-37_S.pdf",
    "ta": "https://documents.gov.lk/view/extra-gazettes/2022/2/2268-37_T.pdf"
  }
}