{
  "doc_type_name": "extra-gazettes",
  "id": "2378-17",
  "dir_data": "data/extra-gazettes/2024/2378-17",
  "doc_num": "2378/17",
  "date": "2024-04-02",
  "description": "Land Title Settlement Department - Mudduwa Samagipura, Ratnapura D/S Division, Ratnapura District - Cad. Map No. 620273",
  "lang_to_source_url": {
    "en": "https://documents.gov.lk/view/extra-gazettes/2024/4/2378-17_E.pdf",
    "si": "https://documents.gov.lk/view/extra-gazettes/2024/4/2378-17_S.pdf",
    "ta": "https://documents.gov.lk/view/extra-gazettes/2024/4/2378-17_T.pdf"
  }
}