{
  "doc_type_name": "extra-gazettes",
  "id": "2025-20",
  "dir_data": "data/extra-gazettes/2017/2025-20",
  "doc_num": "2025/20",
  "date": "2017-06-27",
  "description": "Divisional Secretary Kamburupitiya - Annual Asela Maha Perehara of Sapugoda Ilangamgoda purana Raja Maha Vihara of  Kamburupitiya  Matara District will be held from 06.07.2017 to 13.07.2017",
  "lang_to_source_url": {
    "en": "https://documents.gov.lk/view/extra-gazettes/2017/6/2025-20_E.pdf",
    "si": "https://documents.gov.lk/view/extra-gazettes/2017/6/2025-20_S.pdf",
    "ta": "https://documents.gov.lk/view/extra-gazettes/2017/6/2025-20_T.pdf"
  }
}