{
  "doc_type_name": "extra-gazettes",
  "id": "2349-37",
  "dir_data": "data/extra-gazettes/2023/2349-37",
  "doc_num": "2349/37",
  "date": "2023-09-15",
  "description": "Central Bank of Sri Lanka - Cancellation of License Issued to Kanrich Finance Ltd. due to amalgamation with Nation Lanka Finance PLC. under the Finance Business Act, No 42 of 2011",
  "lang_to_source_url": {
    "en": "https://documents.gov.lk/view/extra-gazettes/2023/9/2349-37_E.pdf",
    "si": "https://documents.gov.lk/view/extra-gazettes/2023/9/2349-37_S.pdf",
    "ta": "https://documents.gov.lk/view/extra-gazettes/2023/9/2349-37_T.pdf"
  }
}