{
  "doc_type_name": "extra-gazettes",
  "id": "1892-29",
  "dir_data": "data/extra-gazettes/2014/1892-29",
  "doc_num": "1892/29",
  "date": "2014-12-10",
  "description": "Department of Commerce - Declaring the Associated Motor Finance Company PLC and other 03 institutions, the Associated Motor Finance Company PLC and another institution and the Citizens Development Business Finance PLC as 'Approved Credit Agencies' for the purposes of the Mortgage Act, the Trust Receipts Ordinance and the Inland Trust Receipts act respectively w.e.f. 08.12.2014",
  "lang_to_source_url": {
    "en": "https://documents.gov.lk/view/extra-gazettes/2014/12/1892-29_E.pdf",
    "si": "https://documents.gov.lk/view/extra-gazettes/2014/12/1892-29_S.pdf",
    "ta": "https://documents.gov.lk/view/extra-gazettes/2014/12/1892-29_T.pdf"
  }
}