{
  "doc_type_name": "extra-gazettes",
  "id": "2005-24",
  "dir_data": "data/extra-gazettes/2017/2005-24",
  "doc_num": "2005/24",
  "date": "2017-02-08",
  "description": "Consumer Affairs Authority - Order to the Maximum Retail Price on Rice w.e.f. 08.02.2017",
  "lang_to_source_url": {
    "en": "https://documents.gov.lk/view/extra-gazettes/2017/2/2005-24_E.pdf",
    "si": "https://documents.gov.lk/view/extra-gazettes/2017/2/2005-24_S.pdf",
    "ta": "https://documents.gov.lk/view/extra-gazettes/2017/2/2005-24_T.pdf"
  }
}