{
  "doc_type_name": "extra-gazettes",
  "id": "1843-12",
  "dir_data": "data/extra-gazettes/2013/1843-12",
  "doc_num": "1843/12",
  "date": "2013-12-31",
  "description": "Land Acquisition - Welikada, Sri Jayawardenapura Kotte D/S Division, Colombo District",
  "lang_to_source_url": {
    "en": "https://documents.gov.lk/view/extra-gazettes/2013/12/1843-12_E.pdf",
    "si": "https://documents.gov.lk/view/extra-gazettes/2013/12/1843-12_S.pdf",
    "ta": "https://documents.gov.lk/view/extra-gazettes/2013/12/1843-12_T.pdf"
  }
}