{
  "doc_type_name": "extra-gazettes",
  "id": "2272-53",
  "dir_data": "data/extra-gazettes/2022/2272-53",
  "doc_num": "2272/53",
  "date": "2022-03-27",
  "description": "Department of Fiscal Policy - The Finance Act, No. 25 of 2003. Order under Section 2(1) amended Extraordinary Gaz. No. 2194/06 dated Sept. 21, 2020",
  "lang_to_source_url": {
    "en": "https://documents.gov.lk/view/extra-gazettes/2022/3/2272-53_E.pdf",
    "si": "https://documents.gov.lk/view/extra-gazettes/2022/3/2272-53_S.pdf",
    "ta": "https://documents.gov.lk/view/extra-gazettes/2022/3/2272-53_T.pdf"
  }
}