{
  "doc_type_name": "extra-gazettes",
  "id": "2085-18",
  "dir_data": "data/extra-gazettes/2018/2085-18",
  "doc_num": "2085/18",
  "date": "2018-08-23",
  "description": "Election Commission - Notify the name of M. L. Silva was selected as a member of the Polonnaruwa Municipal Council",
  "lang_to_source_url": {
    "en": "https://documents.gov.lk/view/extra-gazettes/2018/8/2085-18_E.pdf",
    "si": "https://documents.gov.lk/view/extra-gazettes/2018/8/2085-18_S.pdf",
    "ta": "https://documents.gov.lk/view/extra-gazettes/2018/8/2085-18_T.pdf"
  }
}