{
  "doc_type_name": "extra-gazettes",
  "id": "1885-42",
  "dir_data": "data/extra-gazettes/2014/1885-42",
  "doc_num": "1885/42",
  "date": "2014-10-24",
  "description": "Department of Fiscal Policy - Order to declare that the excise duty on Waters, Cigars, Cigarettes, Motor Vehicles etc. Payable with effect from 25.10.2014",
  "lang_to_source_url": {
    "en": "https://documents.gov.lk/view/extra-gazettes/2014/10/1885-42_E.pdf",
    "si": "https://documents.gov.lk/view/extra-gazettes/2014/10/1885-42_S.pdf",
    "ta": "https://documents.gov.lk/view/extra-gazettes/2014/10/1885-42_T.pdf"
  }
}