{
  "doc_type_name": "extra-gazettes",
  "id": "1952-37",
  "dir_data": "data/extra-gazettes/2016/1952-37",
  "doc_num": "1952/37",
  "date": "2016-02-03",
  "description": "Ministry of Labour and Trade Union Relations - Appointed Mr. R. S. Ariyapperuma as the Arbitrator for settlement of the Industrial Dispute between Mr. G. K. P. G. Fernando of the one part and Ceylinco Leasing Corporation Limited, Ceylinco Capital Investment Company (Private) Limited, Ceylinco Sri Ram Securities Limited of the other part - Order to revoke the Orders made to appoint Mr. W. G. Deen as the Arbitrator for settlement of the Industrial Disputes etween Mr. S. A. Ariyasena and Janashakthi Indurance PLC and between Mr. Sisira de Silva and the Mahaweli Authority of Sri Lanka and appointed Mr. K. M. Sarathchandra and Mr. S. Virithamulla as Arbitrators for settlement of the said Industrial Disputes respectively",
  "lang_to_source_url": {
    "en": "https://documents.gov.lk/view/extra-gazettes/2016/2/1952-37_E.pdf",
    "si": "https://documents.gov.lk/view/extra-gazettes/2016/2/1952-37_S.pdf"
  }
}