{
  "doc_type_name": "extra-gazettes",
  "id": "2416-51",
  "dir_data": "data/extra-gazettes/2024/2416-51",
  "doc_num": "2416/51",
  "date": "2024-12-28",
  "description": "Ministry of Health and Mass Media - Food Act. No. 26 of 1980 Labeling and Advertising Regulations",
  "lang_to_source_url": {
    "en": "https://documents.gov.lk/view/extra-gazettes/2024/12/2416-51_E.pdf",
    "si": "https://documents.gov.lk/view/extra-gazettes/2024/12/2416-51_S.pdf",
    "ta": "https://documents.gov.lk/view/extra-gazettes/2024/12/2416-51_T.pdf"
  }
}