{
  "doc_type_name": "extra-gazettes",
  "id": "2232-40",
  "dir_data": "data/extra-gazettes/2021/2232-40",
  "doc_num": "2232/40",
  "date": "2021-06-18",
  "description": "Presidential Secretariat - Essential Public Services Act, No. 61 of 1979 - Postal Services",
  "lang_to_source_url": {
    "en": "https://documents.gov.lk/view/extra-gazettes/2021/6/2232-40_E.pdf",
    "si": "https://documents.gov.lk/view/extra-gazettes/2021/6/2232-40_S.pdf",
    "ta": "https://documents.gov.lk/view/extra-gazettes/2021/6/2232-40_T.pdf"
  }
}