{
  "doc_type_name": "extra-gazettes",
  "id": "1932-24",
  "dir_data": "data/extra-gazettes/2015/1932-24",
  "doc_num": "1932/24",
  "date": "2015-09-15",
  "description": "Land Title Settlement Department - Mirissa North, Weligama D/S Division, Matara District - Cad. Map No. 820086",
  "lang_to_source_url": {
    "en": "https://documents.gov.lk/view/extra-gazettes/2015/9/1932-24_E.pdf",
    "si": "https://documents.gov.lk/view/extra-gazettes/2015/9/1932-24_S.pdf",
    "ta": "https://documents.gov.lk/view/extra-gazettes/2015/9/1932-24_T.pdf"
  }
}