{
  "doc_type_name": "extra-gazettes",
  "id": "2098-23",
  "dir_data": "data/extra-gazettes/2018/2098-23",
  "doc_num": "2098/23",
  "date": "2018-11-21",
  "description": "Elections Commission - Notice declaring H. D. P. Prasadini and H. P. A. G. Kumari was elected as members of the Maharagama Urban Council",
  "lang_to_source_url": {
    "en": "https://documents.gov.lk/view/extra-gazettes/2018/11/2098-23_E.pdf",
    "si": "https://documents.gov.lk/view/extra-gazettes/2018/11/2098-23_S.pdf",
    "ta": "https://documents.gov.lk/view/extra-gazettes/2018/11/2098-23_T.pdf"
  }
}