{
  "doc_type_name": "extra-gazettes",
  "id": "2292-39",
  "dir_data": "data/extra-gazettes/2022/2292-39",
  "doc_num": "2292/39",
  "date": "2022-08-10",
  "description": "Election Commission - H. H. S. P. Kumara has been Ceased to be a member of the United National Forty of the Lanugamvehera Pradeshiya Sabha",
  "lang_to_source_url": {
    "en": "https://documents.gov.lk/view/extra-gazettes/2022/8/2292-39_E.pdf",
    "si": "https://documents.gov.lk/view/extra-gazettes/2022/8/2292-39_S.pdf",
    "ta": "https://documents.gov.lk/view/extra-gazettes/2022/8/2292-39_T.pdf"
  }
}