{
  "doc_type_name": "extra-gazettes",
  "id": "1858-07",
  "dir_data": "data/extra-gazettes/2014/1858-07",
  "doc_num": "1858/07",
  "date": "2014-04-17",
  "description": "Dept. of Elections - Elected Mr. Wijerathna Mudiyanselage Charika Udayanga Wijerathna as a Member of the Horowpothana Pradeshiya Sabha",
  "lang_to_source_url": {
    "en": "https://documents.gov.lk/view/extra-gazettes/2014/4/1858-07_E.pdf",
    "si": "https://documents.gov.lk/view/extra-gazettes/2014/4/1858-07_S.pdf",
    "ta": "https://documents.gov.lk/view/extra-gazettes/2014/4/1858-07_T.pdf"
  }
}