{
  "doc_type_name": "extra-gazettes",
  "id": "2000-53",
  "dir_data": "data/extra-gazettes/2017/2000-53",
  "doc_num": "2000/53",
  "date": "2017-01-04",
  "description": "Land Acquisition - Madampe and Weralugahamulla, Godakawela D/S Division, Rathnapura District",
  "lang_to_source_url": {
    "en": "https://documents.gov.lk/view/extra-gazettes/2017/1/2000-53_E.pdf",
    "si": "https://documents.gov.lk/view/extra-gazettes/2017/1/2000-53_S.pdf",
    "ta": "https://documents.gov.lk/view/extra-gazettes/2017/1/2000-53_T.pdf"
  }
}