{
  "doc_type_name": "extra-gazettes",
  "id": "2313-68",
  "dir_data": "data/extra-gazettes/2023/2313-68",
  "doc_num": "2313/68",
  "date": "2023-01-07",
  "description": "Ministry of Labour and Foreign Employment - The Industrial Disputes between H. M. W. Abeyrathna No. 90 Matale and other Part Sri Lanka Transport Board Colombo 5 - The Industrial Disputes between M. S. M. Huseni Colombo 13 and other Part Sri Lanka Ports Authorities Colombo 01",
  "lang_to_source_url": {
    "en": "https://documents.gov.lk/view/extra-gazettes/2023/1/2313-68_E.pdf",
    "si": "https://documents.gov.lk/view/extra-gazettes/2023/1/2313-68_S.pdf"
  }
}