{
  "doc_type_name": "extra-gazettes",
  "id": "1813-15",
  "dir_data": "data/extra-gazettes/2013/1813-15",
  "doc_num": "1813/15",
  "date": "2013-06-05",
  "description": "Import and Export Control Dept. - Import and Export (Control) Act No. 1 of 1969 - The Exports (Standardization and Quality Control) Regulations",
  "lang_to_source_url": {
    "en": "https://documents.gov.lk/view/extra-gazettes/2013/6/1813-15_E.pdf",
    "si": "https://documents.gov.lk/view/extra-gazettes/2013/6/1813-15_S.pdf",
    "ta": "https://documents.gov.lk/view/extra-gazettes/2013/6/1813-15_T.pdf"
  }
}