{
  "doc_type_name": "extra-gazettes",
  "id": "2416-23",
  "dir_data": "data/extra-gazettes/2024/2416-23",
  "doc_num": "2416/23",
  "date": "2024-12-26",
  "description": "Land Title Settlement Dept. - Mahanabadawewa, Kebithigollewa D/S Division, Anuradhapura District - Cad. Map No.110402 (24/120083)",
  "lang_to_source_url": {
    "en": "https://documents.gov.lk/view/extra-gazettes/2024/12/2416-23_E.pdf",
    "si": "https://documents.gov.lk/view/extra-gazettes/2024/12/2416-23_S.pdf",
    "ta": "https://documents.gov.lk/view/extra-gazettes/2024/12/2416-23_T.pdf"
  }
}