{
  "doc_type_name": "gazettes",
  "id": "2022-10-28-land-section",
  "dir_data": "data/gazettes/2022/2022-10-28-land-section",
  "doc_num": "2022-10-28-land-section",
  "date": "2022-10-28",
  "description": "Land Section",
  "lang_to_source_url": {
    "en": "https://documents.gov.lk/view/gazettes/2022/10/2022-10-28(III-0)E.pdf",
    "si": "https://documents.gov.lk/view/gazettes/2022/10/2022-10-28(III-0)S.pdf",
    "ta": "https://documents.gov.lk/view/gazettes/2022/10/2022-10-28(III-0)T.pdf"
  }
}