{
  "doc_type_name": "extra-gazettes",
  "id": "2401-32",
  "dir_data": "data/extra-gazettes/2024/2401-32",
  "doc_num": "2401/32",
  "date": "2024-09-13",
  "description": "Presidential Secretariat - Appointment by President Hon.W.S.N.W.B.M.S. Kumari Arambepola state Minister of Health has Resigned from office as the state Minister w.e.f.13.09.2024 and Appointed Hon.W.S.N.W.B.M.S. Kumari Arambepola minister of Parliament as the state Minister of Health Women and Child Affairs w.e.f.13.09.2024.",
  "lang_to_source_url": {
    "en": "https://documents.gov.lk/view/extra-gazettes/2024/9/2401-32_E.pdf",
    "si": "https://documents.gov.lk/view/extra-gazettes/2024/9/2401-32_S.pdf",
    "ta": "https://documents.gov.lk/view/extra-gazettes/2024/9/2401-32_T.pdf"
  }
}