{
  "doc_type_name": "extra-gazettes",
  "id": "2046-09",
  "dir_data": "data/extra-gazettes/2017/2046-09",
  "doc_num": "2046/09",
  "date": "2017-11-21",
  "description": "Land Acquisition - Halwathura, Bulathsinhala D/S Division, Kalutara District",
  "lang_to_source_url": {
    "en": "https://documents.gov.lk/view/extra-gazettes/2017/11/2046-09_E.pdf",
    "si": "https://documents.gov.lk/view/extra-gazettes/2017/11/2046-09_S.pdf",
    "ta": "https://documents.gov.lk/view/extra-gazettes/2017/11/2046-09_T.pdf"
  }
}