{
  "doc_type_name": "extra-gazettes",
  "id": "2192-25",
  "dir_data": "data/extra-gazettes/2020/2192-25",
  "doc_num": "2192/25",
  "date": "2020-09-08",
  "description": "Land Title Settlement Department - Amendment to the Gaz. Ex. No. 2012/46 of 31.03.2017, Minuwangoda D/S Division, and other amendments",
  "lang_to_source_url": {
    "en": "https://documents.gov.lk/view/extra-gazettes/2020/9/2192-25_E.pdf",
    "si": "https://documents.gov.lk/view/extra-gazettes/2020/9/2192-25_S.pdf",
    "ta": "https://documents.gov.lk/view/extra-gazettes/2020/9/2192-25_T.pdf"
  }
}