{
  "doc_type_name": "extra-gazettes",
  "id": "2079-26",
  "dir_data": "data/extra-gazettes/2018/2079-26",
  "doc_num": "2079/26",
  "date": "2018-07-10",
  "description": "Ministry of Labour - Notify the appointments of members to the Wages Boards for the Prawn Culture and Export Trade",
  "lang_to_source_url": {
    "en": "https://documents.gov.lk/view/extra-gazettes/2018/7/2079-26_E.pdf",
    "si": "https://documents.gov.lk/view/extra-gazettes/2018/7/2079-26_S.pdf",
    "ta": "https://documents.gov.lk/view/extra-gazettes/2018/7/2079-26_T.pdf"
  }
}