{
  "doc_type_name": "extra-gazettes",
  "id": "2239-59",
  "dir_data": "data/extra-gazettes/2021/2239-59",
  "doc_num": "2239/59",
  "date": "2021-08-07",
  "description": "Land Title Settlement Department - Homagama, Homagama D/S Division, Colombo District - Cad. Map No. 520001",
  "lang_to_source_url": {
    "en": "https://documents.gov.lk/view/extra-gazettes/2021/8/2239-59_E.pdf",
    "si": "https://documents.gov.lk/view/extra-gazettes/2021/8/2239-59_S.pdf",
    "ta": "https://documents.gov.lk/view/extra-gazettes/2021/8/2239-59_T.pdf"
  }
}