{
  "doc_type_name": "extra-gazettes",
  "id": "2347-13",
  "dir_data": "data/extra-gazettes/2023/2347-13",
  "doc_num": "2347/13",
  "date": "2023-08-31",
  "description": "Presidential Secretariat - The Commission of inquiry enlarge once again the period of time 15th September 2023",
  "lang_to_source_url": {
    "en": "https://documents.gov.lk/view/extra-gazettes/2023/8/2347-13_E.pdf",
    "si": "https://documents.gov.lk/view/extra-gazettes/2023/8/2347-13_S.pdf",
    "ta": "https://documents.gov.lk/view/extra-gazettes/2023/8/2347-13_T.pdf"
  }
}